MANIFEST.in
README.rst
bottle.py
setup.cfg
setup.py
ewer.egg-info/PKG-INFO
ewer.egg-info/SOURCES.txt
ewer.egg-info/dependency_links.txt
ewer.egg-info/top_level.txt
test/__init__.py
test/example_settings.py
test/servertest.py
test/test_app.py
test/test_auth.py
test/test_config.py
test/test_contextlocals.py
test/test_environ.py
test/test_fileupload.py
test/test_formsdict.py
test/test_html_helper.py
test/test_importhook.py
test/test_jinja2.py
test/test_mako.py
test/test_mdict.py
test/test_mount.py
test/test_oorouting.py
test/test_outputfilter.py
test/test_plugins.py
test/test_resources.py
test/test_route.py
test/test_router.py
test/test_securecookies.py
test/test_sendfile.py
test/test_server.py
test/test_stpl.py
test/test_wsgi.py
test/testall.py
test/tools.py
test/views/jinja2_base.tpl
test/views/jinja2_inherit.tpl
test/views/jinja2_simple.tpl
test/views/mako_base.tpl
test/views/mako_inherit.tpl
test/views/mako_simple.tpl
test/views/stpl_include.tpl
test/views/stpl_no_vars.tpl
test/views/stpl_simple.tpl
test/views/stpl_t2base.tpl
test/views/stpl_t2inc.tpl
test/views/stpl_t2main.tpl
test/views/stpl_unicode.tpl